{
  "generatedAt": "2026-04-26T23:51:46.736656+00:00",
  "siteId": "csus-art",
  "label": "CSUS Art",
  "pageCount": 9,
  "linkCount": 109,
  "pages": [
    {
      "id": "87d5e1c2948e1747b059a5dee5ca096320410ff2",
      "siteId": "csus-art",
      "url": "https://www.csus.edu/college/arts-letters/art",
      "title": "Art | Sacramento State",
      "description": "The Art Department at Sacramento State fosters expression through visual arts via courses in art education, art history, ceramics, drawing, new media art, painting, printmaking, and interdisciplinary sculpture.",
      "categories": [
        "degree"
      ],
      "headings": [
        "Department of Art College of Arts & Letters",
        "Announcements",
        "About Art",
        "Academic Programs",
        "Info for Current Art Students",
        "Engage With the World of Art",
        "Art Events on Campus",
        "Campus Services",
        "Connect with the Art Department",
        "Find Us",
        "Contact Us",
        "Meet Us",
        "Follow Us"
      ],
      "contentBlocks": [
        "The Department of Art introduces students to the expressive world of the visual arts. Students are able to explore art through courses in art education, art history, ceramics, drawing, new media art, painting, printmaking, sculpture, and social practice.",
        "The Department\u2019s undergraduate program offers courses in four general areas Art History, Studio Arts Methods, and Art Studio, while the fourth prepares students to teach with a Master of Arts degree in Studio Art .",
        "Thurs, Feb 12 - Thurs, Apr 30 Painting La Comuniversidad",
        "Tues, Apr 28 - Thurs, May 14 Senior Show: Spring 2026",
        "Art Department Kadema Hall, Room 185 Spring Hours, Mon \u2013 Fri, 8AM \u2013 5PM with closures MW 8AM\u20139PM and closure F 3\u20135PM",
        "Follow us on https://www.linkedin.com/groups/13725351/"
      ],
      "links": [
        {
          "url": "../../index.html",
          "text": "Colleges & Majors",
          "hash": "af511004e9a7253a32ecbfc4dfe5d413a70ec71f"
        },
        {
          "url": "../index.html",
          "text": "College of Arts & Letters",
          "hash": "17110f469c89860f51938326587cd2af06299218"
        },
        {
          "url": "index.html",
          "text": "Art",
          "hash": "3629beed8f7a82d3519ef010f84f50f07e438065"
        },
        {
          "url": "https://www.csus.edu/giving/how-you-can-help/new-art-building.html#are-you-ready-to-put-your-name-on-the-future-of-creative-excellence",
          "text": "Donate to the fundraising for new ASL building",
          "hash": "122f1afd837829c296c348c511bebb306ea7c1f4"
        },
        {
          "url": "art-mfa-information.html",
          "text": "MFA in Studio Art Program",
          "hash": "58d1a41f927707752fa227f455f87e728f9ce3e2"
        },
        {
          "url": "advising-information-for-students.html",
          "text": "Advising Information",
          "hash": "60013b7311ea19aa517e6cdbfbaf0d457a00bc9c"
        },
        {
          "url": "safety.html",
          "text": "Facilities & Safety",
          "hash": "d6aeac89058cc04f4b0eb709739d4147cddf9ef3"
        },
        {
          "url": "scholarships.html",
          "text": "Scholarships",
          "hash": "6447c9f940f2f023ccf77de9a6e2f4d868a65fd6"
        },
        {
          "url": "employment.html",
          "text": "Employment Opportunities",
          "hash": "1c01683ba8d4a4f22a3928264c30ede3f8f0c956"
        },
        {
          "url": "_internal/_documents/arts-safety/artdepartment_laptoppolicy_2023.pdf",
          "text": "Laptop Policy for Art Majors",
          "hash": "8b9f1ab3c3c9f35bee7cf81afcb0ce602024da08"
        },
        {
          "url": "art-clubs.html",
          "text": "Art Department Clubs",
          "hash": "d8f1504b6061b8bcdf87bff937a02ad1d81dc122"
        },
        {
          "url": "https://www.csus.edu/university-galleries/index.html",
          "text": "Galleries, Collections, & Spaces",
          "hash": "69b52e0f8faf6bc3333929ff86463102bb7b146b"
        },
        {
          "url": "art-special-events.html",
          "text": "Art Special Events",
          "hash": "e40014ca308ed4f1e60d3b5861bfea4ed420928d"
        },
        {
          "url": "../index.html",
          "text": "The College of Arts & Letters",
          "hash": "2e53b39ff46a70d7b74ab7970cb6d02dc7335e7e"
        },
        {
          "url": "../student-success/index.html",
          "text": "Student Success in Arts & Letters",
          "hash": "eb69f4f1e00e365185605be532d12baf35f3d8dc"
        },
        {
          "url": "../internships-arts-letters.html",
          "text": "Internships in Arts & Letters",
          "hash": "35f5eecd163a2a5b97670c05fcebb39de24559af"
        },
        {
          "url": "https://www.csus.edu/student-life/student-service-center/forms.html",
          "text": "Registrar Forms",
          "hash": "00e0be9234c8108823acf436022f55275c488c9f"
        },
        {
          "url": "https://www.csus.edu/student-affairs/crisis-assistance-resource-education-support/index.html",
          "text": "CARES Office",
          "hash": "a6600f3f717b091c9eeca5c7c570b00173b3f46f"
        },
        {
          "url": "mailto:art@csus.edu",
          "text": "art@csus.edu",
          "hash": "5075877b7fc4f7bcf3abfd510529cffd80211325"
        },
        {
          "url": "meet-us/index.html",
          "text": "Meet Us Icon",
          "hash": "782da9cd820bf1f4d41fb62f4807edaad1873a1b"
        }
      ]
    },
    {
      "id": "6aee8b157d5aa9366afacdaef44b9595b0ea0d91",
      "siteId": "csus-art",
      "url": "https://www.csus.edu/college/arts-letters/art/advising-information-for-students.html",
      "title": "Undergraduate Advising Information for Art Students | Sacramento State",
      "description": "Advising Information for Students",
      "categories": [
        "advising",
        "advisor",
        "major"
      ],
      "headings": [
        "Department of Art College of Arts & Letters",
        "Support Page Content",
        "Undergraduate Advising Information for Art Students",
        "When to Make an Appointment",
        "Preparing for Your First Advising Session",
        "Major Advising Sheets",
        "Minor Advising Sheets"
      ],
      "contentBlocks": [
        "Each undergraduate student who declares an Art major is automatically assigned to an Art Advisor in Art Education, Art History, or Studio Art. All Art Advisors are full-time faculty in the Art Department. Students can work with their assigned advisor or they can request a specific Art faculty member to be their advisor and this request will be reviewed by the Chair. Visit the \"Meet Us\" page for a list of all Art Advisors names, emails, and office hours.",
        "Students are urged to meet with an Art faculty advisor as soon as possible after declaring Art as a major. All Art majors are strongly encouraged to meet with an Art faculty advisor at least once each academic year, usually a few weeks before enrolling in classes for the next term.",
        "When students begin Upper Division coursework in their concentration, it is beneficial to meet again with an advisor to discuss appropriate substitutions, catalog rights, and elective selection. This will better prepare students for applying to graduate and ensure the student is able to complete all the major requirements before their projected graduation date.",
        "When the time comes, students should meet with their advisor again before submitting their online graduation application to confirm the accuracy and completeness of the student\u2019s major requirements.",
        "All full-time Art faculty members advise students during regularly scheduled office hours or by prearranged appointments. Advisor names and contact information are posted on the \"Meet Us\" page and in the Art Office. The Art Office won\u2019t make advisor appointments for students. Email the advisor to arrange an advising appointment if you can\u2019t make it to their office hours.",
        "Collect transcripts as evidence of college level art courses taken at other colleges. Or if records are current, this information can be reviewed on MySacState Student Center. Students should also review the Art major requirements that apply to their Catalog year.",
        "Read information about current lower division transfer agreements for Sacramento State with other CSU campuses and California community colleges on Assist.org . This resource allows advisors to quickly review course articulation agreements. Art courses taken at other institutions may be used toward the major with Art Advisor approval. If necessary, documentation of these courses (catalog descriptions, syllabi, assignments, etc.) may be requested by the Art Advisor. A portfolio of work done in other college art classes may be required to determine equivalency.",
        "Preparing for Your First Advising Session"
      ],
      "links": [
        {
          "url": "../../index.html",
          "text": "Colleges & Majors",
          "hash": "af511004e9a7253a32ecbfc4dfe5d413a70ec71f"
        },
        {
          "url": "../index.html",
          "text": "College of Arts & Letters",
          "hash": "17110f469c89860f51938326587cd2af06299218"
        },
        {
          "url": "index.html",
          "text": "Art",
          "hash": "3629beed8f7a82d3519ef010f84f50f07e438065"
        },
        {
          "url": "advising-information-for-students.html",
          "text": "Undergraduate Advising Information for Art Students",
          "hash": "2cc1a9296744b14be376fa67ed2ba1d38d3c6695"
        },
        {
          "url": "meet-us/index.html",
          "text": "Visit the \"Meet Us\" page",
          "hash": "bb958b5cf0654d866a1d797437ee1d18432c82a2"
        },
        {
          "url": "meet-us/index.html",
          "text": "the \"Meet Us\" page",
          "hash": "9d66cdd9e6f5a8b590c9ac1515efabbf57aac128"
        },
        {
          "url": "_internal/_documents/arts-advising/bfa-studio-art-advising-sheet2.pdf",
          "text": "Studio Art BFA",
          "hash": "7d1a3ff53720b1f49d0cbf1f5a33f9bf683363ee"
        },
        {
          "url": "_internal/_documents/arts-advising/ba-art-advising-sheet1.pdf#BA in Art Advising Sheet",
          "text": "Art BA",
          "hash": "8c1184254bc78d15cdd2492a7dd80ae4f4bbc3f4"
        },
        {
          "url": "_internal/_documents/arts-advising/ba-art-history-advising-sheet.pdf",
          "text": "Art History BA",
          "hash": "ca35935a3d0334e2c86746b71fa9d725295ae36a"
        },
        {
          "url": "_internal/_documents/arts-advising/ba-fine-and-creative-art-art-education-advising-sheet1.pdf",
          "text": "Fine & Creative Arts BA (Art Education)",
          "hash": "cd9d15638971075d8f16fd6c5ed23ef7193ba3d0"
        },
        {
          "url": "_internal/_documents/arts-advising/art-studio-minor-advising-sheet1.pdf",
          "text": "Studio Art Minor",
          "hash": "a08cabce2b6d2d72dd8e06411eab349966aecf67"
        },
        {
          "url": "_internal/_documents/arts-advising/art-history-minor-advising-sheet1.pdf",
          "text": "Art History Minor",
          "hash": "5fcf369bb718be7d6c86ca1df09759ac98d9dada"
        },
        {
          "url": "_internal/_documents/arts-advising/art-education-minor-advising-sheet1.pdf",
          "text": "Art Education Minor",
          "hash": "05d7def0893869f88e18867d6b7d3bfe357f4356"
        },
        {
          "url": "#when-to-make-an-appointment",
          "text": "When to Make an Appointment",
          "hash": "f1c7ecfbc9cf488b0066e738f4df9d40eef3fa9c"
        },
        {
          "url": "#preparing-for-your-first-advising-session",
          "text": "Preparing for Your First Advising Session",
          "hash": "93c8878518d82bc0f2578ca67befac3b0e467077"
        },
        {
          "url": "#major-advising-sheets",
          "text": "Major Advising Sheets",
          "hash": "1abbb2489f2f8209336ba7a894b4cbb31fd59667"
        },
        {
          "url": "#minor-advising-sheets",
          "text": "Minor Advising Sheets",
          "hash": "d5ef097ab7cbc1aba68e12870ff420836d6bc745"
        }
      ]
    },
    {
      "id": "3f54d41ee8b369f77b76345ef79a500ecb0df172",
      "siteId": "csus-art",
      "url": "https://www.csus.edu/college/arts-letters/art/art-mfa-information.html",
      "title": "MFA in Studio Art | Sacramento State",
      "description": "The Master of Fine Arts in Studio Art degree is a two-year, 60-unit, multi-disciplinary and interdisciplinary program in studio art with an emphasis on the individual artist, holistically preparing for a professional career in the arts.",
      "categories": [
        "advisor",
        "scholarship",
        "financial aid",
        "degree"
      ],
      "headings": [
        "Department of Art College of Arts & Letters",
        "Support Page Content",
        "MFA in Studio Art",
        "Overview",
        "Admission Requirements and Procedures",
        "Media Offering & Facilities",
        "Studio Space",
        "Written English Proficiency Requirement",
        "MFA Degree Completion",
        "Graduate Work & Exhibition",
        "Financial Aid, Employment, Scholarships"
      ],
      "contentBlocks": [
        "Fall 2026 Application Deadline is passed.",
        "Check back for our next application period. Application Deadline: Cal State Apply",
        "The Master of Fine Arts in Studio Art degree is a two-year, 60-unit, multi-disciplinary and interdisciplinary program in studio art with an emphasis on the individual artist, holistically preparing for a professional career in the arts.",
        "The Master of Fine Arts in Studio Art offers rigorous study in the discipline, fostering an environment for experimentation, discovery and mastery. The multi-disciplinary and interdisciplinary nature of the program allows artists to work and think across media. The Department of Art has facilities for ceramics, drawing, new media art, painting, printmaking, sculpture, and social practice . MFA students have access to all facilities, studios and shops and each graduate student has a private studio space.",
        "Sacramento is a vibrant city with an active art community and many opportunities for community engagement. Our on-campus galleries hot exhibitions and visiting artists.",
        "The members of the studio faculty are distinguished and active professionals with regional, national and international reputations. Students are guided by the studio faculty, with a studio advisor and the graduate coordinator to mentor them through the program. It is our mission to provide a positive and supportive graduate experience at Sacramento State.",
        "The MFA curriculum includes studio courses, seminars, and courses in art history and in art theory and criticism, with elective opportunities to explore other academic interests. The central focus of the program is the development of bodies of works and the research that supports them. Between five and eight Graduate Students are accepted to the program each Fall. Each incoming cohort is distributed evenly across media. First and second year cohorts meet in seminar and studio courses to discuss their work from diverse perspectives.",
        "For additional information about the MFA in Studio Art, please see the catalogue, course descriptions, Faculty Info, and Admission and Application Procedure in the links below.",
        "Applying to graduate school at Sacramento State entails a simultaneous two part process, and all steps must be completed by the application deadlines. Follow this link to read more about the admission process for our Studio Art MFA.",
        "The Department of Art facilities at Sacramento State are designed to support students\u2019 needs in pursuing various disciplines in studio art. Graduate students have access to all Art Department facilities in consultation with faculty and staff. The facilities are located in:",
        "Kadema Hall: Ceramics, printmaking, painting and drawing, new media art, and social practice spaces.",
        "Mariposa Hall: New media art\u2019s main computer media lab.",
        "Art Studio Lab: Painting and drawing, sculpture, social practice, and graduate program studio spaces.",
        "New Art Studio Lab Facility: including new graduate wing.",
        "The Department of Art has several gallery spaces on campus. Robert Else and R.W. and Joyce Witt Gallery are located at Kadema Hall for student and professional exhibitions. Located in the main library is the University Library Gallery where national and international professional exhibits rotate throughout the year.",
        "All MFA students will have full access to the graduate studios and be assigned a private studio space depending on media discipline. Proximity to labs, shops and equipment is considered when assigning studio spaces. A communal graduate space is located in the Art Sculpture Lab where the majority of graduates\u2019 have their spaces.",
        "All graduate students in the MFA program at Sacramento State must demonstrate graduate level proficiency in writing in accordance with University Graduate Studies standards. This writing proficiency is assessed through ART 206 Art Theory and Criticism, Graduate Writing Intensive (GWI) Course.",
        "Degree completion occurs when the student has fulfilled all University and Departmental requirements of the MFA in Studio Art Degree. This is detailed in the Graduate Handbook that is the graduate students\u2019 guide through the program from admissions to graduation.",
        "The MFA program requires successful completion of all core and elective course work, successful completion of all semester reviews and Advancement to Candidacy solo exhibition review.",
        "In the last term of the degree students will enroll in ART 500A and ART 500B Culminating Experience Exhibition and Thesis in which the final exhibition review and submission of written abstract (thesis) will be assessed by the Faculty.",
        "Sacramento State has financial aid packages available and are recommended to apply for financial aid by priority date of March 2nd for Fall admissions, although applicants may apply at any time after priority date. The two-year MFA program is $4,518 per semester. On average, students can anticipate approximately $18,000 in total tuition costs. Out-of-State applicants can anticipate an additional $396 per unit for the first year or until residency is established. Tuition and fees are subject to annual precentage increases.",
        "The MFA program also offers opportunities in teaching, art technician work and gallery operations in various forms including Federal Work Study.",
        "Pay rates are per semester Federal work study $1,000-1,500 Instructional Student Assistant (ISA) $2,000-4,800 Graduate Assistant (GA) $2,000-3,300 Teaching Associate (TA) $3,200-4,500",
        "Graduate Scholarships Annual student scholarships and awards range from $800 to $5,000; each has its own unique requirements.Art Department scholarships include the Jennette B. Yuppa Scholarship, Ruth Rippon Ceramics Scholarship, and the ACE Scholarship.",
        "For a more information please visit the links below."
      ],
      "links": [
        {
          "url": "../../index.html",
          "text": "Colleges & Majors",
          "hash": "af511004e9a7253a32ecbfc4dfe5d413a70ec71f"
        },
        {
          "url": "../index.html",
          "text": "College of Arts & Letters",
          "hash": "17110f469c89860f51938326587cd2af06299218"
        },
        {
          "url": "index.html",
          "text": "Art",
          "hash": "3629beed8f7a82d3519ef010f84f50f07e438065"
        },
        {
          "url": "art-mfa-information.html",
          "text": "MFA in Studio Art",
          "hash": "61d444af9a8b861eb69b0a569f9140b4838bf626"
        },
        {
          "url": "meet-us/index.html",
          "text": "Art Faculty",
          "hash": "e976e5e453f8bdb66e251fb0f8042e7d5423aae9"
        },
        {
          "url": "art-mfa-admissions.html",
          "text": "Admission Requirements and Procedures",
          "hash": "360efd2f97f28efb1f36630561e46aa5f93de87f"
        },
        {
          "url": "https://www.csus.edu/university-galleries/else-gallery/index.html",
          "text": "Robert Else",
          "hash": "94907552a3e32ceafbbc5147d12d50628d9d72e0"
        },
        {
          "url": "https://www.csus.edu/university-galleries/witt-gallery/index.html",
          "text": "R.W. and Joyce Witt Gallery",
          "hash": "eb8e81b4068745aff90a93e6b542c4b913ed83d1"
        },
        {
          "url": "https://www.csus.edu/university-galleries/library-galleries/index.html",
          "text": "University Library Gallery",
          "hash": "eb1c9a1b706eb38af2915865763eb1cbc609a537"
        },
        {
          "url": "https://www.csus.edu/university-galleries/index.html",
          "text": "University Galleries",
          "hash": "bedb6364edcc75072eb25c8e560a2ab697a5367e"
        },
        {
          "url": "https://www.csus.edu/university-galleries/library-galleries/exhibitions/mfa-2023/index.html",
          "text": "View the 2023 Inaugural MFA Exhibition",
          "hash": "b8ded785fc28f07ffc73853d18a432287c2eeca0"
        },
        {
          "url": "https://www.csus.edu/administration-business-affairs/bursar/tuition-living-costs.html",
          "text": "Current Sac State Tuition Info",
          "hash": "059d4e5b4b74c85589d523b835aa5b75bada1c5d"
        },
        {
          "url": "https://www.csus.edu/apply/financial-aid-scholarships/index.html",
          "text": "Financial Aid and Scholarships",
          "hash": "d86f5b7bb08f525615c783125a2fa1279f4cbe8c"
        },
        {
          "url": "scholarships.html",
          "text": "Art Scholarships",
          "hash": "fccc095cea52b90b4e823284ede8787406fa01b7"
        },
        {
          "url": "../../../graduate-studies/unit-11/how-to-apply.html",
          "text": "ISA, GA, TA",
          "hash": "5ef7479a0dec82544e319ecd3123dbecd70c6ee9"
        },
        {
          "url": "#overview",
          "text": "Overview",
          "hash": "f1892bb51621875b9261dd99d5793c27a51de45e"
        },
        {
          "url": "#admission-requirements-and-procedures",
          "text": "Admission Requirements and Procedures",
          "hash": "f4bf562cf95e5c3a362291979eb6d7d64321231f"
        },
        {
          "url": "#media-offering-facilities",
          "text": "Media Offering & Facilities",
          "hash": "8244b3fab3ddbf735aecbaa3c58d4bdc02000e68"
        },
        {
          "url": "#studio-space",
          "text": "Studio Space",
          "hash": "ce912f7354b2b06e25bea99c78ae2ab3228e0c88"
        },
        {
          "url": "#written-english-proficiency-requirement",
          "text": "Written English Proficiency Requirement",
          "hash": "09fed161312890323a9717ba8d1e5bdcf06b4285"
        },
        {
          "url": "#mfa-degree-completion",
          "text": "MFA Degree Completion",
          "hash": "4172af42c8a78868a41439f90313ef5799d89628"
        },
        {
          "url": "#graduate-work-exhibition",
          "text": "Graduate Work & Exhibition",
          "hash": "ec3e8a5dca424b67005a5ccb078266699c8e1c81"
        },
        {
          "url": "#financial-aid-employment-scholarships",
          "text": "Financial Aid, Employment, Scholarships",
          "hash": "9339d2c354241a6742da8cc4fc3d12c31d7903e2"
        }
      ]
    },
    {
      "id": "ab2950d60b5de5cfb58508d594e17926c53d1634",
      "siteId": "csus-art",
      "url": "https://www.csus.edu/college/arts-letters/art/scholarships.html",
      "title": "Scholarships | Sacramento State",
      "description": "The Department of Art sponsors over eight scholarships and awards programs for its students each year. Applications for these awards are accepted- and winners are announced- each Spring semester. Each semester, the Department hires Sacramento State students to as graders, studio assistants, and gallery monitors.",
      "categories": [
        "scholarship",
        "major"
      ],
      "headings": [
        "Department of Art College of Arts & Letters",
        "Support Page Content",
        "Scholarships",
        "Scholarships on Sac State's Scholarship Portal",
        "Awards Available in the Annual Student Award Show",
        "R.W. and Joyce Witt Art History Competition"
      ],
      "contentBlocks": [
        "The Department of Art sponsors several scholarships and awards programs for its students each year. Applications for these awards are accepted starting in October and winners are announced each Spring semester. To be eligible to win one of these scholarships, applicants must be active students and meet that scholarship's individual eligibility requirements during the semester the money will be awarded.",
        "The deadline to apply for these scholarships is March 2, 2026 at 11:59 pm. Both the scholarship and award recipients will be announced at the Annual Awards Show in Spring 2026.",
        "Apply now on Sac State's Scholarship Portal!",
        "The Academic and Creative Excellence Award is a $1000 award to support an outstanding undergraduate or graduate Art major. Open to Sophomore, Junior, Senior, and Graduate students in good academic standing and an overall GPA of 2.0 for Undergrad and 3.0 for Grad.",
        "The Jeannette B. Yuppa Scholarship is a $1000 award to support an outstanding undergraduate or graduate Art major who has chosen teaching at any level as a future goal. Two recipients are chosen a year.",
        "The Marla Chicconi Memorial Endowed Art Scholarship is a $1500 award to support an outstanding undergraduate Art major with an interest in teaching. Open to Sophomore, Junior, and Senior students with a declared major in Art and an overall GPA of 2.0.",
        "The Juanita and Jose Montoya Memorial Art Scholarship is a $1500 award to support an outstanding undergraduate Art major with an interest in teaching. Open to Junior and Senior students with a declared major in Art and an overall GPA of 2.7.",
        "The ClayPeople Award is an award to support an undergrad or graduate Art student who is enrolled in a ceramics course in the year that they apply. A portfolio is required.",
        "The Ruth Rippon Ceramic Scholarship is a $1000 award offered once a year to an outstanding student majoring in Studio Art, with an emphasis in ceramics, who shows promise in making ceramic art a career.",
        "The Peggy Saunders Hall Memorial Scholarship is a $5,000 award to support an outstanding undergraduate Art student who has chosen teaching at any level as a future goal.",
        "The Department of Art and the University Galleries hold their annual Awards Show each spring. The exhibition is juried by two guest jurors and features work by current art students. The Awards Show exhibition includes several award categories as well as merit awards. The competition is open to undergraduate and graduate students, as well as all matriculated and Open University students, enrolled at Sac State during the current academic year. Below are available monetary awards available to students.",
        "The R. W. and Joyce Witt Scholarship Award in Studio Art for any Sacramento State student with a declared minor or major in Art or Photography. All media are eligible. Award amount varies per year.",
        "The Frederick M. Peyser, Sr. Prize in Studio Art for any Sacramento State undergraduate. Only two-dimensional media (painting, photography, printmaking, mixed media, and digital, video and interactive works) are eligible. Award amount varies per year.",
        "The Increase Robinson Memorial Fellowship Award is for classified graduate students in Studio Art. Entries may be in any medium. Each award is $1000. This award may be won only once.",
        "The R. W. and Joyce Witt Art History Competition gives out two awards of $200 each. One prize will be awarded for each of the two following categories. Students can submit one entry to each category.",
        "Category A: graduate or undergraduate art history research papers .",
        "Category B: graduate or undergraduate art writing of any genre .",
        "A faculty sponsor is required for each submission. Any applicant must be enrolled at Sacramento State in Spring 2026 and must have a declared major or minor in Art or Photography. Any graduate student must have classified status and must be enrolled in the Studio Art MFA program or in a special major MA program in art, art history, art education, or art administration.",
        "Check back here in January 2026 for more information about our Spring 2026 competition!",
        "Scholarships on Sac State's Scholarship Portal",
        "Awards Available in the Annual Student Award Show",
        "R.W. and Joyce Witt Art History Competition"
      ],
      "links": [
        {
          "url": "../../index.html",
          "text": "Colleges & Majors",
          "hash": "af511004e9a7253a32ecbfc4dfe5d413a70ec71f"
        },
        {
          "url": "../index.html",
          "text": "Arts & Letters",
          "hash": "c2cfb57ce54936ed973bd3ea1b3e76692132d5fd"
        },
        {
          "url": "index.html",
          "text": "Art",
          "hash": "3629beed8f7a82d3519ef010f84f50f07e438065"
        },
        {
          "url": "scholarships.html",
          "text": "Scholarships",
          "hash": "6447c9f940f2f023ccf77de9a6e2f4d868a65fd6"
        },
        {
          "url": "#scholarships-on-sac-state-s-scholarship-portal",
          "text": "Scholarships on Sac State's Scholarship Portal",
          "hash": "32f710a501f5aecaddbd1fd8d456531448256ca1"
        },
        {
          "url": "#awards-available-in-the-annual-student-award-show",
          "text": "Awards Available in the Annual Student Award Show",
          "hash": "30c1ab8d5ae78a3cb81d07413e93fdd479e16b3f"
        },
        {
          "url": "#rw-and-joyce-witt-art-history-competition",
          "text": "R.W. and Joyce Witt Art History Competition",
          "hash": "94395695e518ba5eebbc77e1def6f19218bda9fa"
        }
      ]
    },
    {
      "id": "0a55f8901911f4878c47bcc775a04aa3926e6c57",
      "siteId": "csus-art",
      "url": "https://www.csus.edu/college/arts-letters/art/employment.html",
      "title": "Employment Opportunities | Sacramento State",
      "description": "Sac State Art Department Employment Opportunities.",
      "categories": [],
      "headings": [
        "Department of Art College of Arts & Letters",
        "Support Page Content",
        "Employment Opportunities",
        "Part-Time Teaching",
        "Part-Time Art Models",
        "Instructional Support Assistant Student Positions",
        "Federal Work Study Student Positions"
      ],
      "contentBlocks": [
        "The Department of Art anticipates a need for part-time instructors. Salary rate is variable depending upon qualifications and relevant experience.",
        "Applications will remain open until filled.",
        "Please visit our new Career site linked below for the position details, list of qualifications, and applicant instructions. To be considered to teach in 2025-2026 , please submit your materials, following the guidelines provided in the link. 3YR contract faculty need only submit if they are in the third year of a three-year contract.",
        "Apply for the 2025/26 Art Department Lecturer Pool",
        "The Art Department is now accepting applications for our part-time Art Model hiring pool . Modeling is in the nude and involves a variety of poses sustained over varying periods of time. Skills required include the ability to hold poses requested by the Art instructor over specified periods of time (short gestural or action poses, longer poses for more detailed studies of the figure, etc.). Apply today! Pool will open again soon!",
        "The Art Department employs Instructional Student Assistants to provide support as studio assistants in the New Media and Printmaking labs, and as graders for large Art History lecture classes. Upper division and graduate students are encouraged to apply for Academic Student Employee positions. Hiring criteria vary with each type of job and is subject to funding.",
        "All positions have been filled for the Fall 2025 semester, please check back in January for Spring hiring information.",
        "Federal Work Study positions are also available to provide support in the Art Studio Lab and to work as an Inventory and Media Assistant. Students must be awarded Federal Work Study to be considered.",
        "FWS Technician Assistants will help with the general class use of lab facilities and will function as directed in maintaining a clean and safe work environment in all areas operated by the Art department.",
        "The FWS Inventory and Media Assistant will assist in the development and execution of a new inventory system and the set up of the new virtual reality lab."
      ],
      "links": [
        {
          "url": "../../index.html",
          "text": "Colleges & Majors",
          "hash": "af511004e9a7253a32ecbfc4dfe5d413a70ec71f"
        },
        {
          "url": "../index.html",
          "text": "Arts & Letters",
          "hash": "c2cfb57ce54936ed973bd3ea1b3e76692132d5fd"
        },
        {
          "url": "index.html",
          "text": "Art",
          "hash": "3629beed8f7a82d3519ef010f84f50f07e438065"
        },
        {
          "url": "employment.html",
          "text": "Employment Opportunities",
          "hash": "1c01683ba8d4a4f22a3928264c30ede3f8f0c956"
        },
        {
          "url": "#employment-opportunities",
          "text": "Employment Opportunities",
          "hash": "d35320cb82c90bbe516e7ecae07cc9283533ff85"
        }
      ]
    },
    {
      "id": "dccac80076d87ee8c7abf4a94635b95bda7e7b27",
      "siteId": "csus-art",
      "url": "https://www.csus.edu/college/arts-letters/art/art-clubs.html",
      "title": "Art Clubs | Sacramento State",
      "description": "The Art Department's variety of clubs connects students and artists to get involved in events and exhibitions regardless of discipline or media.",
      "categories": [
        "advisor"
      ],
      "headings": [
        "Department of Art College of Arts & Letters",
        "Support Page Content",
        "Art Clubs",
        "Art History Club",
        "Ceramics Guild",
        "Printmaking Club",
        "Sac State Chapter of the National Art Education Association"
      ],
      "contentBlocks": [
        "The Art Department has a variety of clubs that students can get involved in, no matter what their focus is.",
        "Joining an art club can help connect you to other student artists and artists in the greater Sacramento community, and is a great way to get involved in events and exhibitions and gain valuable new experiences.",
        "The Art History Club at Sac State strives to build a community of artists, historians, educators, and students of all disciplines. We hope to create opportunities for students to have an outreach into the Sacramento art community through a variety of events such as films, second Saturday events and museum visits. Faculty advisor: Rachel Miller",
        "The purpose of the Ceramic Guild is to increase interest in the ceramic department, raise money for new equipment, and gain new experiences. This is a club for both students and members of the Sacramento community. Faculty advisor: Scott Parady",
        "Printmaking has a rich history of making art, information and revolutionary ideas available to the public. In the Printmaking Club, the aim is to revive the art and science of traditional printmaking within our campus community. Members are accepted from all academic disciplines. No printmaking experience required. Faculty advisor: Summer Ventis",
        "The Sacramento State student chapter of NAEA is coming this Fall 2019. This is the world\u2019s largest professional art education association with over 20,000 members across the country. Membership is open to art students, art museum educators, non-art educators, teaching artists, and studio artists. A membership would be to the state and national associations with no additional cost. Faculty advisor: Luis-Genaro Garcia"
      ],
      "links": [
        {
          "url": "../../index.html",
          "text": "Colleges & Majors",
          "hash": "af511004e9a7253a32ecbfc4dfe5d413a70ec71f"
        },
        {
          "url": "../index.html",
          "text": "Arts & Letters",
          "hash": "c2cfb57ce54936ed973bd3ea1b3e76692132d5fd"
        },
        {
          "url": "index.html",
          "text": "Art",
          "hash": "3629beed8f7a82d3519ef010f84f50f07e438065"
        },
        {
          "url": "art-clubs.html",
          "text": "Art Clubs",
          "hash": "a8783c1c3be8fdbf482f513e545cb7109657b588"
        },
        {
          "url": "mailto:arthistoryclub.csus@gmail.com",
          "text": "Art History Club",
          "hash": "dd6d6f9b7042fd73bcd52881af9945ec2675a495"
        },
        {
          "url": "mailto:rachel.miller@saclink.csus.edu",
          "text": "Rachel Miller",
          "hash": "9a832579795c132db7f9b5a5db2f7a51a5ceeaec"
        },
        {
          "url": "mailto:sparady@csus.edu",
          "text": "Scott Parady",
          "hash": "525931055d19fb1e44e664af8948a7d050950686"
        },
        {
          "url": "mailto:summer.ventis@csus.edu",
          "text": "Summer Ventis",
          "hash": "b88709111ecd42c2cadcfc8f46ec54334c349dce"
        },
        {
          "url": "mailto:luis.garcia@csus.edu",
          "text": "Luis-Genaro Garcia",
          "hash": "a94e20a553b0b5d8e3fb502e63f7a69c3b999e00"
        }
      ]
    },
    {
      "id": "83d590298fc73f7dc71332fffe7881da82e9d798",
      "siteId": "csus-art",
      "url": "https://www.csus.edu/college/arts-letters/art/art-special-events.html",
      "title": "Events in the Art Department | Sacramento State",
      "description": "The Department of Art sponsors an array of free public events throughout the year. Enjoy the many exhibitions, lectures, and more on the Sacramento State campus.",
      "categories": [
        "scholarship"
      ],
      "headings": [
        "Department of Art College of Arts & Letters",
        "Support Page Content",
        "Events in the Art Department",
        "Witt Gallery Submissions",
        "Annual Student Awards Show",
        "Festival of the Arts",
        "Faculty-Led Study Abroad",
        "Art Ball"
      ],
      "contentBlocks": [
        "The Department of Art sponsors a full array of free public events at Sacramento State each year including art exhibitions by faculty, students and visiting artists, visiting scholar lectures, the Annual Student Awards Show, the Art History Symposium and the end of year Art Ball.",
        "All of the artistic media taught in the Department of Art are represented in the Robert Else Gallery and R.W. & Joyce Witt Gallery in Kadema Hall. Most of the shows are designed and installed by Art students. Students and faculty are frequently involved in the University Union Gallery and University Library Gallery exhibitions.",
        "Admission to events sponsored by the Department of Art is free and open to the public.",
        "R.W. & Joyce Witt Gallery proposals are accepted by the Gallery & Events Committee each spring for consideration for the following academic year. Refer to the Witt Gallery Exhibition Guide and to the Witt Gallery Application for details and deadlines. Witt Gallery exhibitors are responsible for funding, publicizing, installing and staffing the exhibitions.",
        "Check back here in Spring 2026 for information on how to apply for the 2026/2027 academic year.",
        "The Department of Art and the University Galleries hold their annual Awards Show each spring. The exhibition is juried by two guest jurors and features work by current art students. The Awards Show exhibition includes several award categories as well as merit awards. You can read about the requirements for each category on our Scholarships page . We encourage you to apply if you are eligible. The competition is open to undergraduate and graduate students, as well as all matriculated and Open University students, enrolled at Sac State during the current academic year.",
        "Congrats to all of our Awards Show and Scholarship recipients! We encourage all students to apply again next year!",
        "Each spring, the College of Arts & Letters presents a showcase of all A&L programs through a week-long celebration. The Art Department participates through workshops, visiting artists and lectures, and the Art History Symposium. Stay tuned for more details about FOTA 2026!",
        "Find Out More About the Festival of the Arts",
        "The Department of Art is pleased to announce that the Art History program will be offering an Italy study abroad course again in January 2026. Experience art in person in Italy and use the cities of Rome and Florence as your classroom. This nine-day program is designed to make art more accessible for participants and will focus on art of the Italian peninsula from the ancient period to the year 1800. Visits to the Colosseum, Roman Forum, Vatican, and Palazzo Medici are some of the many highlights of this program!",
        "Read more about studying abroad in Italy!",
        "At the end of every Spring semester, we hold a huge celebration that spans across all areas of the Art Department and all galleries on campus called Art Ball. This is a chance to honor the hard work of all our Art students at once before we leave for summer break."
      ],
      "links": [
        {
          "url": "../../index.html",
          "text": "Colleges & Majors",
          "hash": "af511004e9a7253a32ecbfc4dfe5d413a70ec71f"
        },
        {
          "url": "../index.html",
          "text": "Arts & Letters",
          "hash": "c2cfb57ce54936ed973bd3ea1b3e76692132d5fd"
        },
        {
          "url": "index.html",
          "text": "Art",
          "hash": "3629beed8f7a82d3519ef010f84f50f07e438065"
        },
        {
          "url": "art-special-events.html",
          "text": "Events in the Art Department",
          "hash": "bd0be2b25c2806fbb1b6034aa5e051d85728b565"
        },
        {
          "url": "https://www.csus.edu/university-galleries/else-gallery/index.html",
          "text": "Robert Else Gallery",
          "hash": "1f829ace4fd5f294104ed8d347cb3402e5968392"
        },
        {
          "url": "https://www.csus.edu/university-galleries/witt-gallery/index.html",
          "text": "R.W. & Joyce Witt Gallery",
          "hash": "5eb4d2293c1d8ff0cf819257026be26dc9250867"
        },
        {
          "url": "https://www.csus.edu/university-galleries/library-galleries/index.html",
          "text": "University Library Gallery",
          "hash": "eb1c9a1b706eb38af2915865763eb1cbc609a537"
        },
        {
          "url": "_internal/_documents/arts-events/witt-exhibition-guide-2024-25.pdf",
          "text": "Refer to the Witt Gallery Exhibition Guide",
          "hash": "421edfbea5ab6bce41a55b39fee323c9f4553025"
        },
        {
          "url": "scholarships.html",
          "text": "You can read about the requirements for each category on our Scholarships page",
          "hash": "b794d00e1259dbd55672c8ca37ab31ff2bcfbed9"
        },
        {
          "url": "../festival-of-the-arts/index.html",
          "text": "Find Out More About the Festival of the Arts",
          "hash": "a05d40c8adab8ce213ff7da2b5eb51fb238a93ee"
        }
      ]
    },
    {
      "id": "f7c475177c9dc750271d2b7b448e293b858a4948",
      "siteId": "csus-art",
      "url": "https://www.csus.edu/college/arts-letters/art/safety.html",
      "title": "Facilities & Safety in the Art Department | Sacramento State",
      "description": "The Department of Art is an advocate for maintaining a studio environment that in the interest of preventing reasonably avoidable harm, accidental injury or illness, shall encourage the preservation of health and safety for all populations who use the studio art facilities in pursuit of higher learning and community outreach.",
      "categories": [],
      "headings": [
        "Department of Art College of Arts & Letters",
        "Support Page Content",
        "Facilities & Safety in the Art Department",
        "Facilities & Studios",
        "Art Studio Lab Key Issue",
        "Art Studio Lab Hours",
        "Kadema Lab Hours"
      ],
      "contentBlocks": [
        "The Department of Art utilizes the following on-campus buildings and facilities for instruction in the studio disciplines:",
        "Kadema Hall houses the Art Department office, faculty offices, Art Education and Art History classrooms, studios for Ceramics, Printmaking, Beginning Painting and Drawing, the New Media Art lab facilities and the Witt and Else Galleries.",
        "Mariposa Hall 1007 houses the New Media Art computer labs.",
        "Art Studio Lab houses technician and faculty offices, graduate student's individual studios, shops and studios for Sculpture, Painting, and Drawing.",
        "Students currently enrolled in Art Studio classes are encouraged to get a key fob to grant access to the studio facilities and resources, as well as to keep students safe during open lab hours, especially after hours. Students may only be issued keys or fobs if their faculty has requested their access.",
        "If approved for a key or fob by your faculty:",
        "If you are already in enrolled in a class that has been approved for a key/fob, it will be ready to be picked up from Facilities Management in the first week of the semester.",
        "If you enroll late in a class that has been approved for a key/fob, it will not be ready to be picked up from Facilities Management until Census.",
        "Visit Facilities Management to pick up your key/fob, if you do not already have one. The office is located at the front of campus, along the J street side of campus off Bay Laurel Way, behind the Athletics Center.",
        "Return the key/fob to Facilities Management at the end of the semester/year."
      ],
      "links": [
        {
          "url": "../../index.html",
          "text": "Colleges & Majors",
          "hash": "af511004e9a7253a32ecbfc4dfe5d413a70ec71f"
        },
        {
          "url": "../index.html",
          "text": "College of Arts & Letters",
          "hash": "17110f469c89860f51938326587cd2af06299218"
        },
        {
          "url": "index.html",
          "text": "Art",
          "hash": "3629beed8f7a82d3519ef010f84f50f07e438065"
        },
        {
          "url": "safety.html",
          "text": "Facilities & Safety in the Art Department",
          "hash": "d2fd842719ef4fab8430f1e47a209c59d5c1d0b1"
        },
        {
          "url": "#facilities-studios",
          "text": "Facilities & Studios",
          "hash": "d83f9050572aec26ece41960512a8679104db061"
        },
        {
          "url": "#art-studio-lab-key-issue",
          "text": "Art Studio Lab Key Issue",
          "hash": "7b068d36dad1bd3608979d75a00287a3fcccf366"
        },
        {
          "url": "#art-studio-lab-hours",
          "text": "Art Studio Lab Hours",
          "hash": "f3de891d1039ee158ddf0525d1d1ba87cd7f7e57"
        },
        {
          "url": "#kadema-lab-hours",
          "text": "Kadema Lab Hours",
          "hash": "e4a633d38395e0ca3960e0997556786b6cdb1109"
        }
      ]
    },
    {
      "id": "205280896e615b435d97ac100e00f0f71150f113",
      "siteId": "csus-art",
      "url": "https://www.csus.edu/college/arts-letters/art/meet-us",
      "title": "Meet Us | Art | Sacramento State",
      "description": "Office Hours: Faculty: Monday, 2:30 - 4:30pm & Tuesday, 3 - 5pm Student: Monday, 12:30pm - 2:30pm & Friday, 11am - 1pm, By Appointment",
      "categories": [
        "advisor"
      ],
      "headings": [
        "Department of Art College of Arts & Letters",
        "Meet Us",
        "Department Chair",
        "Rachel Miller",
        "Staff",
        "Michelle Cordova",
        "Benjamin Hunt",
        "Vex Rios",
        "Kevin Ptak",
        "Quinn Terrones",
        "Kate Wallace",
        "Full-Time Faculty/ Art Advisors",
        "Yipaer Aierken",
        "Rachel Clarke",
        "Andrew Connelly",
        "Mya Dosch",
        "Sarah Flohr",
        "Luis-Genaro Garcia",
        "Ian Harvey",
        "Rey Jeong",
        "Robert Ortbal",
        "Scott Parady",
        "Summer Ventis",
        "Adero Willard",
        "Peter Williams",
        "Part-Time Faculty",
        "Nata\u00f1a Aldana-Lowe",
        "Joy Bertinuson",
        "Sloane Cabrera",
        "Andrew Cain",
        "Ricardo Chavez",
        "Jodi Connelly",
        "Kerry Cottle",
        "Mark Emerson",
        "Paula Flohr",
        "Jill Hannon",
        "Mercy Hawkins",
        "Joanna Kidd",
        "Hunter Kiley",
        "Houghton Kinsman",
        "Elise Mahan",
        "Jeff Mayry",
        "Shadieh Mirmobiny",
        "Bradley Oblenes",
        "Chuck Owens",
        "Denise Rogers",
        "Laurie Seban",
        "William J. Simmons",
        "Frank Stockton",
        "Olga Tymoshchuk",
        "Sala Wong",
        "Justin Wood"
      ],
      "contentBlocks": [
        "Office Hours: Faculty: Monday, 2:30 - 4:30pm & Tuesday, 3 - 5pm Student: Monday, 12:30pm - 2:30pm & Friday, 11am - 1pm, By Appointment",
        "Areas of Teaching: Art History, Early Modern European Art",
        "Office Hours: Tues/Thurs 12:00pm - 1:30pm in person",
        "Areas of Teaching: Art History; Asian Art",
        "Office Hours: Tues/Thurs 10:50am-12:20pm by appointment, using booking link",
        "Areas of Teaching: Art Studio; New Media",
        "Areas of Teaching: Art Studio; Sculpture",
        "Office Hours: Mon 1:30-3:30pm; Tues 11:30-12:30pm in-person or email for Zoom",
        "Areas of Teaching: Art History; Art of the Americas",
        "Office Hours: Mon & Weds 7am - 8:30am by appointment",
        "Areas of Teaching: Art Studio; Drawing & Painting",
        "Office Hours: Tues and Thurs 11am - 12:30pm",
        "Office Hours: Tues 3-5pm; Thurs 3-4pm in-person only; must email in advance for appt",
        "Office Hours: Mon 11am-2pm must make appt by email or via booking link",
        "Areas of Teaching: Art Studio; Social Practice Art",
        "Office Hours: Mon & Weds 12pm - 1pm & 7pm - 7:30pm",
        "Office Hours: Tues and Thurs 10:50am - 11:50am & 5:50pm - 6:20pm",
        "MFA Graduate Coordinator & Associate Professor",
        "Office Hours: Tues 10:30am-12pm; Wed 2-3:30pm and by appt; in-person or via Zoom meeting ID: 992 5586 6181",
        "Areas of Teaching: Art Studio; Printmaking",
        "Office Hours: Thurs 3pm - 5pm & Tues 9am - 10am Zoom by appointment",
        "Office Hours: Tues 11:00 am-12:30pm in-person Thurs 3:30pm-5pm Zoom; Email w/ 24 hr notice for appt",
        "Areas of Teaching: Art Studio; New Media Art",
        "Office Hours: Mon/Wed 2:30-3:30pm via Zoom, Mon/Wed 5:45-6:15pm in-person in MRP 1000",
        "Office Hours: Mon 7-8pm in-person or by appt",
        "Office Hours: Tues/Thurs 10:30-11:30am in-person",
        "Office Hours: Tues and Thurs 11:30am - 12pm & 5:50pm - 6:20pm",
        "Office Hours: Wed 1-2pm in office or KDM 170",
        "Office Hours: Mon/Wed 11:50am-1pm, KDM 190 or KDM 104/107",
        "Office Hours: HONR 3 Thurs 11am-12pm in-person; AH105 Weds 11am-12pm via Zoom",
        "Office Hours: Tues 4-5pm in-person or virtual & by appt",
        "Office Hours: Tues/Thurs 12-1pm, Fri 3-4pm appt only, in-person or virtual by request",
        "Office Hours: ART2-01 Mon 11am-12pm; ART2-02 Mon 7-8pm ART2-03 Tues 11am-12pm",
        "Office Hours: Mon/Wed 5-6:30pm in-person or via Zoom",
        "Office Hours: Wed 1-2pm via Zoom meeting ID: 811 7630 0168",
        "Office Hours: Tues/Thurs 3:30\u20133:55pm by appt. Contact via Canvas w/ 24 hr notice in-person/Zoom",
        "Office Hours: Wed 1-3pm virtual; please email w/ 24 hr notice for appt",
        "Office Hours: Mon 11am-12pm in-person or Zoom; please email w/ 24 hr notice for appt"
      ],
      "links": [
        {
          "url": "../../../index.html",
          "text": "Colleges & Majors",
          "hash": "806e545f9aecd08fdb97c5882fa5c808a424823d"
        },
        {
          "url": "../../index.html",
          "text": "College of Arts & Letters",
          "hash": "d512f3c6cac5d0ce44a2e5db3e87f1f45ad8b029"
        },
        {
          "url": "../index.html",
          "text": "Art",
          "hash": "a73a2eb9f09faa5002d73347c5debe3f5d01a00e"
        },
        {
          "url": "index.html",
          "text": "Meet Us",
          "hash": "650d01d60b6f3f0788e5aede5c650766e286f557"
        },
        {
          "url": "#department-chair",
          "text": "Department Chair",
          "hash": "8eda08e3c12dd936304229a503e7153d3543d5e0"
        },
        {
          "url": "#staff",
          "text": "Staff",
          "hash": "418a02a9219e7e8cd2e17e769adc1bde1444c960"
        },
        {
          "url": "#full-time-faculty-art-advisors",
          "text": "Full-Time Faculty/ Art Advisors",
          "hash": "7cd3d05b10d1150d2d8c289567b463a14a7fdaf8"
        },
        {
          "url": "#part-time-faculty",
          "text": "Part-Time Faculty",
          "hash": "8afbc13d8c1c6581648e34cd50f0664388f3a651"
        },
        {
          "url": "mailto:rachel.miller@csus.edu",
          "text": "rachel.miller@csus.edu",
          "hash": "d229ef1650bdb2e24e20370f9b818a4a6168b033"
        },
        {
          "url": "mailto:michelle.cordova@csus.edu",
          "text": "michelle.cordova@csus.edu",
          "hash": "cedb25daeb4b473705bee6f76e62cf064a40850f"
        },
        {
          "url": "mailto:benjamin.hunt@csus.edu",
          "text": "benjamin.hunt@csus.edu",
          "hash": "1119aaec0692f794d4e429e78d9c207d58e176cf"
        },
        {
          "url": "mailto:mariamariscal@csus.edu",
          "text": "mariamariscal@csus.edu",
          "hash": "e366b1cde498c5a4d315a74e5dea782edf48f0ab"
        },
        {
          "url": "mailto:sac19940@csus.edu",
          "text": "sac19940@csus.edu",
          "hash": "1bcd34be7b4107bbd31e2289e1f14e3fc2968324"
        },
        {
          "url": "mailto:cquinn2@csus.edu",
          "text": "cquinn2@csus.edu",
          "hash": "4af77e1008a45eacb66710b2b94993404ec4486e"
        },
        {
          "url": "mailto:katewallace@csus.edu",
          "text": "katewallace@csus.edu",
          "hash": "40d5a12cb21eb92eb2c75959166d4054e5366dac"
        },
        {
          "url": "mailto:a.yipaer@csus.edu",
          "text": "a.yipaer@csus.edu",
          "hash": "e08079dd16dccc23502b9f12329adcc4bbea24e9"
        },
        {
          "url": "mailto:rclarke@csus.edu",
          "text": "rclarke@csus.edu",
          "hash": "81840facc17c7d3269fa99400f51f62c1715fcca"
        },
        {
          "url": "mailto:connelly@csus.edu",
          "text": "connelly@csus.edu",
          "hash": "a5934911a4c75441239b5583a3e1790e9332d1f0"
        },
        {
          "url": "mailto:dosch@csus.edu",
          "text": "dosch@csus.edu",
          "hash": "a7266effb3ad7d3e0184be085633733955eed3c9"
        },
        {
          "url": "mailto:sflohr@csus.edu",
          "text": "sflohr@csus.edu",
          "hash": "5704bed8e0986e3047648303b97d955bbc299240"
        },
        {
          "url": "mailto:luis.garcia@csus.edu",
          "text": "luis.garcia@csus.edu",
          "hash": "2cc4fecd5e85b5b91b5c0fc3db0a05b9dee81395"
        },
        {
          "url": "mailto:iharvey@csus.edu",
          "text": "iharvey@csus.edu",
          "hash": "5fda57c0b847aee9bada0629c938cbec3dd3a983"
        },
        {
          "url": "mailto:rey.jeong@csus.edu",
          "text": "rey.jeong@csus.edu",
          "hash": "4f14d5fdf90588154ba1f51dffe382e749196bc4"
        },
        {
          "url": "mailto:ortbal@csus.edu",
          "text": "ortbal@csus.edu",
          "hash": "a39889b251719dd1778f08f73e4a4778eb70c562"
        },
        {
          "url": "mailto:sparady@csus.edu",
          "text": "sparady@csus.edu",
          "hash": "1f814fd03bfc2e6de97a9262f28c683b5a6fd43a"
        },
        {
          "url": "mailto:summer.ventis@csus.edu",
          "text": "summer.ventis@csus.edu",
          "hash": "1a26b9ace4f02e50f23670c05b91ab9f456827b9"
        },
        {
          "url": "mailto:a.willard@csus.edu",
          "text": "a.willard@csus.edu",
          "hash": "7ce5e41ccdba76ac3c361b07fdc137a458ab05a3"
        },
        {
          "url": "mailto:peter.williams@csus.edu",
          "text": "peter.williams@csus.edu",
          "hash": "e4bdc198f06a6b8873798513654f981045332b59"
        },
        {
          "url": "mailto:n.aldana-lowe@csus.edu",
          "text": "n.aldana-lowe@csus.edu",
          "hash": "04bf68f79ad4170979feb5004ed19cc73a3699c8"
        },
        {
          "url": "mailto:joy.bertinuson@csus.edu",
          "text": "joy.bertinuson@csus.edu",
          "hash": "98265915eb7b9d10e305e875477abbb374be2774"
        },
        {
          "url": "mailto:sloanecabrera@csus.edu",
          "text": "sloanecabrera@csus.edu",
          "hash": "b45e29dd26a13c21497c844d0e7bce65047e8635"
        },
        {
          "url": "mailto:a.cain@csus.edu",
          "text": "a.cain@csus.edu",
          "hash": "ada424f61ebc1ff9e0a4ba82c3280e8bada119ab"
        },
        {
          "url": "mailto:ricardo.chavez@csus.edu",
          "text": "ricardo.chavez@csus.edu",
          "hash": "7564c1e46ad0f90a1361067ddead7291bafe5f7b"
        },
        {
          "url": "mailto:j.connelly@csus.edu",
          "text": "j.connelly@csus.edu",
          "hash": "f8716aa0c7a24ef78acbca6019181efb20a05d4e"
        },
        {
          "url": "mailto:k.cottle@csus.edu",
          "text": "k.cottle@csus.edu",
          "hash": "06bdc82b72fd92411d8f3de670f5d0d50035bf6e"
        },
        {
          "url": "mailto:sac59379@csus.edu",
          "text": "sac59379@csus.edu",
          "hash": "fc7ca4c3be0cf230542f65cdafc06185f9490f73"
        },
        {
          "url": "mailto:paula.j.flohr@csus.edu",
          "text": "paula.j.flohr@csus.edu",
          "hash": "1f9921df98d31e6018fb390cb1f685a4ad1ed6ef"
        },
        {
          "url": "mailto:jillhannon@csus.edu",
          "text": "jillhannon@csus.edu",
          "hash": "080c13b4f5d4c1098a4e5d5c02b75245d4fc42fa"
        },
        {
          "url": "mailto:mercy.hawkins@csus.edu",
          "text": "mercy.hawkins@csus.edu",
          "hash": "fbcb3b56700b05fde1bdf8d12ef408e2d448de95"
        },
        {
          "url": "mailto:j.kidd@csus.edu",
          "text": "j.kidd@csus.edu",
          "hash": "302a2e23fca160f0756e6ac064d7105b359d772a"
        },
        {
          "url": "mailto:h.kiley@csus.edu",
          "text": "h.kiley@csus.edu",
          "hash": "566bfd3e09fd205b6b69b495da29dad4bda1948c"
        },
        {
          "url": "mailto:h.kinsman@csus.edu",
          "text": "h.kinsman@csus.edu",
          "hash": "8e57f8a20026512a902537b06b3cf714d11e8c68"
        },
        {
          "url": "mailto:pmahan2@csus.edu",
          "text": "pmahan2@csus.edu",
          "hash": "d79a14d77bed80110438247f08a29fd7e5418624"
        },
        {
          "url": "mailto:jeffrey.mayry@csus.edu",
          "text": "jeffrey.mayry@csus.edu",
          "hash": "8b6a5043581e959dcbce00e5e00ad7967e02310d"
        },
        {
          "url": "mailto:shadieh.mirmobiny@csus.edu",
          "text": "shadieh.mirmobiny@csus.edu",
          "hash": "9dff5081100f5170b3711addb236d0b322b03140"
        },
        {
          "url": "mailto:bradleyoblenes@csus.edu",
          "text": "bradleyoblenes@csus.edu",
          "hash": "cea86dacfa30e90649ccd2315bb8b0acd53ed697"
        },
        {
          "url": "mailto:r.c.owens@csus.edu",
          "text": "r.c.owens@csus.edu",
          "hash": "7321fdb64e5879a64cbfb75526f8e5778aea5459"
        },
        {
          "url": "mailto:denise.rogers@csus.edu",
          "text": "denise.rogers@csus.edu",
          "hash": "ff248bb9244be4152374ed76ec3ea257eccdf8a2"
        },
        {
          "url": "mailto:lseban@csus.edu",
          "text": "lseban@csus.edu",
          "hash": "b193ed5229d2f53d21a57e7af7a9afc1f2c762a1"
        },
        {
          "url": "mailto:william.j.simmons@csus.edu",
          "text": "william.j.simmons@csus.edu",
          "hash": "fa29ece63da1361bf9c00c2cc0d635e314f2085f"
        },
        {
          "url": "mailto:stockton@csus.edu",
          "text": "stockton@csus.edu",
          "hash": "f368d55290bc6be4b2229c34d84f2ecd84a6748b"
        },
        {
          "url": "mailto:otymoshchuk@csus.edu",
          "text": "otymoshchuk@csus.edu",
          "hash": "87454fe5743b2c24a22ae7b2e85e103fb08c3a24"
        },
        {
          "url": "mailto:c.wong@csus.edu",
          "text": "c.wong@csus.edu",
          "hash": "2bcd589e9771b0369c75f46eeedf05205d9a1d2a"
        },
        {
          "url": "mailto:j.wood@csus.edu",
          "text": "j.wood@csus.edu",
          "hash": "1f08f0bac458947273743323727f1ae21ac37316"
        }
      ]
    }
  ],
  "links": [
    {
      "url": "../../index.html",
      "text": "Colleges & Majors",
      "hash": "af511004e9a7253a32ecbfc4dfe5d413a70ec71f"
    },
    {
      "url": "../index.html",
      "text": "College of Arts & Letters",
      "hash": "17110f469c89860f51938326587cd2af06299218"
    },
    {
      "url": "index.html",
      "text": "Art",
      "hash": "3629beed8f7a82d3519ef010f84f50f07e438065"
    },
    {
      "url": "https://www.csus.edu/giving/how-you-can-help/new-art-building.html#are-you-ready-to-put-your-name-on-the-future-of-creative-excellence",
      "text": "Donate to the fundraising for new ASL building",
      "hash": "122f1afd837829c296c348c511bebb306ea7c1f4"
    },
    {
      "url": "art-mfa-information.html",
      "text": "MFA in Studio Art Program",
      "hash": "58d1a41f927707752fa227f455f87e728f9ce3e2"
    },
    {
      "url": "advising-information-for-students.html",
      "text": "Advising Information",
      "hash": "60013b7311ea19aa517e6cdbfbaf0d457a00bc9c"
    },
    {
      "url": "safety.html",
      "text": "Facilities & Safety",
      "hash": "d6aeac89058cc04f4b0eb709739d4147cddf9ef3"
    },
    {
      "url": "scholarships.html",
      "text": "Scholarships",
      "hash": "6447c9f940f2f023ccf77de9a6e2f4d868a65fd6"
    },
    {
      "url": "employment.html",
      "text": "Employment Opportunities",
      "hash": "1c01683ba8d4a4f22a3928264c30ede3f8f0c956"
    },
    {
      "url": "_internal/_documents/arts-safety/artdepartment_laptoppolicy_2023.pdf",
      "text": "Laptop Policy for Art Majors",
      "hash": "8b9f1ab3c3c9f35bee7cf81afcb0ce602024da08"
    },
    {
      "url": "art-clubs.html",
      "text": "Art Department Clubs",
      "hash": "d8f1504b6061b8bcdf87bff937a02ad1d81dc122"
    },
    {
      "url": "https://www.csus.edu/university-galleries/index.html",
      "text": "Galleries, Collections, & Spaces",
      "hash": "69b52e0f8faf6bc3333929ff86463102bb7b146b"
    },
    {
      "url": "art-special-events.html",
      "text": "Art Special Events",
      "hash": "e40014ca308ed4f1e60d3b5861bfea4ed420928d"
    },
    {
      "url": "../student-success/index.html",
      "text": "Student Success in Arts & Letters",
      "hash": "eb69f4f1e00e365185605be532d12baf35f3d8dc"
    },
    {
      "url": "../internships-arts-letters.html",
      "text": "Internships in Arts & Letters",
      "hash": "35f5eecd163a2a5b97670c05fcebb39de24559af"
    },
    {
      "url": "https://www.csus.edu/student-life/student-service-center/forms.html",
      "text": "Registrar Forms",
      "hash": "00e0be9234c8108823acf436022f55275c488c9f"
    },
    {
      "url": "https://www.csus.edu/student-affairs/crisis-assistance-resource-education-support/index.html",
      "text": "CARES Office",
      "hash": "a6600f3f717b091c9eeca5c7c570b00173b3f46f"
    },
    {
      "url": "mailto:art@csus.edu",
      "text": "art@csus.edu",
      "hash": "5075877b7fc4f7bcf3abfd510529cffd80211325"
    },
    {
      "url": "meet-us/index.html",
      "text": "Meet Us Icon",
      "hash": "782da9cd820bf1f4d41fb62f4807edaad1873a1b"
    },
    {
      "url": "_internal/_documents/arts-advising/bfa-studio-art-advising-sheet2.pdf",
      "text": "Studio Art BFA",
      "hash": "7d1a3ff53720b1f49d0cbf1f5a33f9bf683363ee"
    },
    {
      "url": "_internal/_documents/arts-advising/ba-art-advising-sheet1.pdf#BA in Art Advising Sheet",
      "text": "Art BA",
      "hash": "8c1184254bc78d15cdd2492a7dd80ae4f4bbc3f4"
    },
    {
      "url": "_internal/_documents/arts-advising/ba-art-history-advising-sheet.pdf",
      "text": "Art History BA",
      "hash": "ca35935a3d0334e2c86746b71fa9d725295ae36a"
    },
    {
      "url": "_internal/_documents/arts-advising/ba-fine-and-creative-art-art-education-advising-sheet1.pdf",
      "text": "Fine & Creative Arts BA (Art Education)",
      "hash": "cd9d15638971075d8f16fd6c5ed23ef7193ba3d0"
    },
    {
      "url": "_internal/_documents/arts-advising/art-studio-minor-advising-sheet1.pdf",
      "text": "Studio Art Minor",
      "hash": "a08cabce2b6d2d72dd8e06411eab349966aecf67"
    },
    {
      "url": "_internal/_documents/arts-advising/art-history-minor-advising-sheet1.pdf",
      "text": "Art History Minor",
      "hash": "5fcf369bb718be7d6c86ca1df09759ac98d9dada"
    },
    {
      "url": "_internal/_documents/arts-advising/art-education-minor-advising-sheet1.pdf",
      "text": "Art Education Minor",
      "hash": "05d7def0893869f88e18867d6b7d3bfe357f4356"
    },
    {
      "url": "#when-to-make-an-appointment",
      "text": "When to Make an Appointment",
      "hash": "f1c7ecfbc9cf488b0066e738f4df9d40eef3fa9c"
    },
    {
      "url": "#preparing-for-your-first-advising-session",
      "text": "Preparing for Your First Advising Session",
      "hash": "93c8878518d82bc0f2578ca67befac3b0e467077"
    },
    {
      "url": "#major-advising-sheets",
      "text": "Major Advising Sheets",
      "hash": "1abbb2489f2f8209336ba7a894b4cbb31fd59667"
    },
    {
      "url": "#minor-advising-sheets",
      "text": "Minor Advising Sheets",
      "hash": "d5ef097ab7cbc1aba68e12870ff420836d6bc745"
    },
    {
      "url": "art-mfa-admissions.html",
      "text": "Admission Requirements and Procedures",
      "hash": "360efd2f97f28efb1f36630561e46aa5f93de87f"
    },
    {
      "url": "https://www.csus.edu/university-galleries/else-gallery/index.html",
      "text": "Robert Else",
      "hash": "94907552a3e32ceafbbc5147d12d50628d9d72e0"
    },
    {
      "url": "https://www.csus.edu/university-galleries/witt-gallery/index.html",
      "text": "R.W. and Joyce Witt Gallery",
      "hash": "eb8e81b4068745aff90a93e6b542c4b913ed83d1"
    },
    {
      "url": "https://www.csus.edu/university-galleries/library-galleries/index.html",
      "text": "University Library Gallery",
      "hash": "eb1c9a1b706eb38af2915865763eb1cbc609a537"
    },
    {
      "url": "https://www.csus.edu/university-galleries/library-galleries/exhibitions/mfa-2023/index.html",
      "text": "View the 2023 Inaugural MFA Exhibition",
      "hash": "b8ded785fc28f07ffc73853d18a432287c2eeca0"
    },
    {
      "url": "https://www.csus.edu/administration-business-affairs/bursar/tuition-living-costs.html",
      "text": "Current Sac State Tuition Info",
      "hash": "059d4e5b4b74c85589d523b835aa5b75bada1c5d"
    },
    {
      "url": "https://www.csus.edu/apply/financial-aid-scholarships/index.html",
      "text": "Financial Aid and Scholarships",
      "hash": "d86f5b7bb08f525615c783125a2fa1279f4cbe8c"
    },
    {
      "url": "../../../graduate-studies/unit-11/how-to-apply.html",
      "text": "ISA, GA, TA",
      "hash": "5ef7479a0dec82544e319ecd3123dbecd70c6ee9"
    },
    {
      "url": "#overview",
      "text": "Overview",
      "hash": "f1892bb51621875b9261dd99d5793c27a51de45e"
    },
    {
      "url": "#admission-requirements-and-procedures",
      "text": "Admission Requirements and Procedures",
      "hash": "f4bf562cf95e5c3a362291979eb6d7d64321231f"
    },
    {
      "url": "#media-offering-facilities",
      "text": "Media Offering & Facilities",
      "hash": "8244b3fab3ddbf735aecbaa3c58d4bdc02000e68"
    },
    {
      "url": "#studio-space",
      "text": "Studio Space",
      "hash": "ce912f7354b2b06e25bea99c78ae2ab3228e0c88"
    },
    {
      "url": "#written-english-proficiency-requirement",
      "text": "Written English Proficiency Requirement",
      "hash": "09fed161312890323a9717ba8d1e5bdcf06b4285"
    },
    {
      "url": "#mfa-degree-completion",
      "text": "MFA Degree Completion",
      "hash": "4172af42c8a78868a41439f90313ef5799d89628"
    },
    {
      "url": "#graduate-work-exhibition",
      "text": "Graduate Work & Exhibition",
      "hash": "ec3e8a5dca424b67005a5ccb078266699c8e1c81"
    },
    {
      "url": "#financial-aid-employment-scholarships",
      "text": "Financial Aid, Employment, Scholarships",
      "hash": "9339d2c354241a6742da8cc4fc3d12c31d7903e2"
    },
    {
      "url": "#scholarships-on-sac-state-s-scholarship-portal",
      "text": "Scholarships on Sac State's Scholarship Portal",
      "hash": "32f710a501f5aecaddbd1fd8d456531448256ca1"
    },
    {
      "url": "#awards-available-in-the-annual-student-award-show",
      "text": "Awards Available in the Annual Student Award Show",
      "hash": "30c1ab8d5ae78a3cb81d07413e93fdd479e16b3f"
    },
    {
      "url": "#rw-and-joyce-witt-art-history-competition",
      "text": "R.W. and Joyce Witt Art History Competition",
      "hash": "94395695e518ba5eebbc77e1def6f19218bda9fa"
    },
    {
      "url": "#employment-opportunities",
      "text": "Employment Opportunities",
      "hash": "d35320cb82c90bbe516e7ecae07cc9283533ff85"
    },
    {
      "url": "mailto:arthistoryclub.csus@gmail.com",
      "text": "Art History Club",
      "hash": "dd6d6f9b7042fd73bcd52881af9945ec2675a495"
    },
    {
      "url": "mailto:rachel.miller@saclink.csus.edu",
      "text": "Rachel Miller",
      "hash": "9a832579795c132db7f9b5a5db2f7a51a5ceeaec"
    },
    {
      "url": "mailto:sparady@csus.edu",
      "text": "Scott Parady",
      "hash": "525931055d19fb1e44e664af8948a7d050950686"
    },
    {
      "url": "mailto:summer.ventis@csus.edu",
      "text": "Summer Ventis",
      "hash": "b88709111ecd42c2cadcfc8f46ec54334c349dce"
    },
    {
      "url": "mailto:luis.garcia@csus.edu",
      "text": "Luis-Genaro Garcia",
      "hash": "a94e20a553b0b5d8e3fb502e63f7a69c3b999e00"
    },
    {
      "url": "_internal/_documents/arts-events/witt-exhibition-guide-2024-25.pdf",
      "text": "Refer to the Witt Gallery Exhibition Guide",
      "hash": "421edfbea5ab6bce41a55b39fee323c9f4553025"
    },
    {
      "url": "../festival-of-the-arts/index.html",
      "text": "Find Out More About the Festival of the Arts",
      "hash": "a05d40c8adab8ce213ff7da2b5eb51fb238a93ee"
    },
    {
      "url": "#facilities-studios",
      "text": "Facilities & Studios",
      "hash": "d83f9050572aec26ece41960512a8679104db061"
    },
    {
      "url": "#art-studio-lab-key-issue",
      "text": "Art Studio Lab Key Issue",
      "hash": "7b068d36dad1bd3608979d75a00287a3fcccf366"
    },
    {
      "url": "#art-studio-lab-hours",
      "text": "Art Studio Lab Hours",
      "hash": "f3de891d1039ee158ddf0525d1d1ba87cd7f7e57"
    },
    {
      "url": "#kadema-lab-hours",
      "text": "Kadema Lab Hours",
      "hash": "e4a633d38395e0ca3960e0997556786b6cdb1109"
    },
    {
      "url": "../../../index.html",
      "text": "Colleges & Majors",
      "hash": "806e545f9aecd08fdb97c5882fa5c808a424823d"
    },
    {
      "url": "#department-chair",
      "text": "Department Chair",
      "hash": "8eda08e3c12dd936304229a503e7153d3543d5e0"
    },
    {
      "url": "#staff",
      "text": "Staff",
      "hash": "418a02a9219e7e8cd2e17e769adc1bde1444c960"
    },
    {
      "url": "#full-time-faculty-art-advisors",
      "text": "Full-Time Faculty/ Art Advisors",
      "hash": "7cd3d05b10d1150d2d8c289567b463a14a7fdaf8"
    },
    {
      "url": "#part-time-faculty",
      "text": "Part-Time Faculty",
      "hash": "8afbc13d8c1c6581648e34cd50f0664388f3a651"
    },
    {
      "url": "mailto:rachel.miller@csus.edu",
      "text": "rachel.miller@csus.edu",
      "hash": "d229ef1650bdb2e24e20370f9b818a4a6168b033"
    },
    {
      "url": "mailto:michelle.cordova@csus.edu",
      "text": "michelle.cordova@csus.edu",
      "hash": "cedb25daeb4b473705bee6f76e62cf064a40850f"
    },
    {
      "url": "mailto:benjamin.hunt@csus.edu",
      "text": "benjamin.hunt@csus.edu",
      "hash": "1119aaec0692f794d4e429e78d9c207d58e176cf"
    },
    {
      "url": "mailto:mariamariscal@csus.edu",
      "text": "mariamariscal@csus.edu",
      "hash": "e366b1cde498c5a4d315a74e5dea782edf48f0ab"
    },
    {
      "url": "mailto:sac19940@csus.edu",
      "text": "sac19940@csus.edu",
      "hash": "1bcd34be7b4107bbd31e2289e1f14e3fc2968324"
    },
    {
      "url": "mailto:cquinn2@csus.edu",
      "text": "cquinn2@csus.edu",
      "hash": "4af77e1008a45eacb66710b2b94993404ec4486e"
    },
    {
      "url": "mailto:katewallace@csus.edu",
      "text": "katewallace@csus.edu",
      "hash": "40d5a12cb21eb92eb2c75959166d4054e5366dac"
    },
    {
      "url": "mailto:a.yipaer@csus.edu",
      "text": "a.yipaer@csus.edu",
      "hash": "e08079dd16dccc23502b9f12329adcc4bbea24e9"
    },
    {
      "url": "mailto:rclarke@csus.edu",
      "text": "rclarke@csus.edu",
      "hash": "81840facc17c7d3269fa99400f51f62c1715fcca"
    },
    {
      "url": "mailto:connelly@csus.edu",
      "text": "connelly@csus.edu",
      "hash": "a5934911a4c75441239b5583a3e1790e9332d1f0"
    },
    {
      "url": "mailto:dosch@csus.edu",
      "text": "dosch@csus.edu",
      "hash": "a7266effb3ad7d3e0184be085633733955eed3c9"
    },
    {
      "url": "mailto:sflohr@csus.edu",
      "text": "sflohr@csus.edu",
      "hash": "5704bed8e0986e3047648303b97d955bbc299240"
    },
    {
      "url": "mailto:iharvey@csus.edu",
      "text": "iharvey@csus.edu",
      "hash": "5fda57c0b847aee9bada0629c938cbec3dd3a983"
    },
    {
      "url": "mailto:rey.jeong@csus.edu",
      "text": "rey.jeong@csus.edu",
      "hash": "4f14d5fdf90588154ba1f51dffe382e749196bc4"
    },
    {
      "url": "mailto:ortbal@csus.edu",
      "text": "ortbal@csus.edu",
      "hash": "a39889b251719dd1778f08f73e4a4778eb70c562"
    },
    {
      "url": "mailto:a.willard@csus.edu",
      "text": "a.willard@csus.edu",
      "hash": "7ce5e41ccdba76ac3c361b07fdc137a458ab05a3"
    },
    {
      "url": "mailto:peter.williams@csus.edu",
      "text": "peter.williams@csus.edu",
      "hash": "e4bdc198f06a6b8873798513654f981045332b59"
    },
    {
      "url": "mailto:n.aldana-lowe@csus.edu",
      "text": "n.aldana-lowe@csus.edu",
      "hash": "04bf68f79ad4170979feb5004ed19cc73a3699c8"
    },
    {
      "url": "mailto:joy.bertinuson@csus.edu",
      "text": "joy.bertinuson@csus.edu",
      "hash": "98265915eb7b9d10e305e875477abbb374be2774"
    },
    {
      "url": "mailto:sloanecabrera@csus.edu",
      "text": "sloanecabrera@csus.edu",
      "hash": "b45e29dd26a13c21497c844d0e7bce65047e8635"
    },
    {
      "url": "mailto:a.cain@csus.edu",
      "text": "a.cain@csus.edu",
      "hash": "ada424f61ebc1ff9e0a4ba82c3280e8bada119ab"
    },
    {
      "url": "mailto:ricardo.chavez@csus.edu",
      "text": "ricardo.chavez@csus.edu",
      "hash": "7564c1e46ad0f90a1361067ddead7291bafe5f7b"
    },
    {
      "url": "mailto:j.connelly@csus.edu",
      "text": "j.connelly@csus.edu",
      "hash": "f8716aa0c7a24ef78acbca6019181efb20a05d4e"
    },
    {
      "url": "mailto:k.cottle@csus.edu",
      "text": "k.cottle@csus.edu",
      "hash": "06bdc82b72fd92411d8f3de670f5d0d50035bf6e"
    },
    {
      "url": "mailto:sac59379@csus.edu",
      "text": "sac59379@csus.edu",
      "hash": "fc7ca4c3be0cf230542f65cdafc06185f9490f73"
    },
    {
      "url": "mailto:paula.j.flohr@csus.edu",
      "text": "paula.j.flohr@csus.edu",
      "hash": "1f9921df98d31e6018fb390cb1f685a4ad1ed6ef"
    },
    {
      "url": "mailto:jillhannon@csus.edu",
      "text": "jillhannon@csus.edu",
      "hash": "080c13b4f5d4c1098a4e5d5c02b75245d4fc42fa"
    },
    {
      "url": "mailto:mercy.hawkins@csus.edu",
      "text": "mercy.hawkins@csus.edu",
      "hash": "fbcb3b56700b05fde1bdf8d12ef408e2d448de95"
    },
    {
      "url": "mailto:j.kidd@csus.edu",
      "text": "j.kidd@csus.edu",
      "hash": "302a2e23fca160f0756e6ac064d7105b359d772a"
    },
    {
      "url": "mailto:h.kiley@csus.edu",
      "text": "h.kiley@csus.edu",
      "hash": "566bfd3e09fd205b6b69b495da29dad4bda1948c"
    },
    {
      "url": "mailto:h.kinsman@csus.edu",
      "text": "h.kinsman@csus.edu",
      "hash": "8e57f8a20026512a902537b06b3cf714d11e8c68"
    },
    {
      "url": "mailto:pmahan2@csus.edu",
      "text": "pmahan2@csus.edu",
      "hash": "d79a14d77bed80110438247f08a29fd7e5418624"
    },
    {
      "url": "mailto:jeffrey.mayry@csus.edu",
      "text": "jeffrey.mayry@csus.edu",
      "hash": "8b6a5043581e959dcbce00e5e00ad7967e02310d"
    },
    {
      "url": "mailto:shadieh.mirmobiny@csus.edu",
      "text": "shadieh.mirmobiny@csus.edu",
      "hash": "9dff5081100f5170b3711addb236d0b322b03140"
    },
    {
      "url": "mailto:bradleyoblenes@csus.edu",
      "text": "bradleyoblenes@csus.edu",
      "hash": "cea86dacfa30e90649ccd2315bb8b0acd53ed697"
    },
    {
      "url": "mailto:r.c.owens@csus.edu",
      "text": "r.c.owens@csus.edu",
      "hash": "7321fdb64e5879a64cbfb75526f8e5778aea5459"
    },
    {
      "url": "mailto:denise.rogers@csus.edu",
      "text": "denise.rogers@csus.edu",
      "hash": "ff248bb9244be4152374ed76ec3ea257eccdf8a2"
    },
    {
      "url": "mailto:lseban@csus.edu",
      "text": "lseban@csus.edu",
      "hash": "b193ed5229d2f53d21a57e7af7a9afc1f2c762a1"
    },
    {
      "url": "mailto:william.j.simmons@csus.edu",
      "text": "william.j.simmons@csus.edu",
      "hash": "fa29ece63da1361bf9c00c2cc0d635e314f2085f"
    },
    {
      "url": "mailto:stockton@csus.edu",
      "text": "stockton@csus.edu",
      "hash": "f368d55290bc6be4b2229c34d84f2ecd84a6748b"
    },
    {
      "url": "mailto:otymoshchuk@csus.edu",
      "text": "otymoshchuk@csus.edu",
      "hash": "87454fe5743b2c24a22ae7b2e85e103fb08c3a24"
    },
    {
      "url": "mailto:c.wong@csus.edu",
      "text": "c.wong@csus.edu",
      "hash": "2bcd589e9771b0369c75f46eeedf05205d9a1d2a"
    },
    {
      "url": "mailto:j.wood@csus.edu",
      "text": "j.wood@csus.edu",
      "hash": "1f08f0bac458947273743323727f1ae21ac37316"
    }
  ]
}